configmaster/INIConfigFile.py
configmaster/ConfigFile.py
configmaster/__init__.py
configmaster/JSONConfigFile.py
configmaster/YAMLConfigFile.py
configmaster/SPyCfg.py
configmaster/exc.py
configmaster/ConfigKey.py
configmaster/ConfigGenerator.py
ConfigMaster-2.3.5.post1.dist-info/RECORD
ConfigMaster-2.3.5.post1.dist-info/top_level.txt
ConfigMaster-2.3.5.post1.dist-info/METADATA
ConfigMaster-2.3.5.post1.dist-info/WHEEL
ConfigMaster-2.3.5.post1.dist-info/DESCRIPTION.rst
ConfigMaster-2.3.5.post1.dist-info/metadata.json
