Metadata-Version: 2.0
Name: ConfigMaster
Version: 2.3.5.post1
Summary: Programmatic configuration library for Python 3.
Home-page: https://github.com/SunDwarf/ConfigMaster
Author: Isaac Dickinson
Author-email: eyesismine@gmail.com
License: MIT
Platform: UNKNOWN
Classifier: Development Status :: 5 - Production/Stable
Classifier: License :: OSI Approved :: MIT License
Classifier: Operating System :: OS Independent
Classifier: Programming Language :: Python :: 3 :: Only
